{ "height":36,
 "layers":[
        {
         "data":[4, 4, 4, 4, 4, 4, 4, 4, 4, 4, 4, 4, 4, 4, 4, 4, 4, 4, 4, 4, 4, 4, 4, 4, 4, 4, 4, 4, 4, 4, 4, 4, 4, 4, 4, 4, 4, 4, 4, 4, 4, 4, 4, 4, 4, 4, 4, 4, 4, 4, 4, 4, 4, 4, 4, 4, 4, 1, 1, 1, 1, 1, 1, 1, 1, 1, 1, 1, 1, 4, 4, 1, 1, 1, 1, 1, 1, 1, 1, 1, 1, 1, 1, 4, 4, 1, 2, 2, 2, 2, 1, 2, 2, 2, 2, 2, 1, 4, 4, 1, 2, 2, 2, 2, 2, 1, 2, 2, 2, 2, 1, 4, 4, 1, 2, 2, 2, 2, 1, 2, 2, 2, 2, 2, 1, 4, 4, 1, 2, 2, 2, 2, 2, 1, 2, 2, 2, 2, 1, 4, 4, 1, 2, 2, 2, 2, 1, 2, 2, 2, 2, 2, 1, 4, 4, 1, 2, 2, 2, 2, 2, 1, 2, 2, 2, 2, 1, 4, 4, 1, 1, 1, 1, 1, 1, 1, 1, 1, 1, 1, 1, 1, 1, 1, 1, 1, 1, 1, 1, 1, 1, 1, 1, 1, 1, 4, 4, 1, 2, 2, 2, 2, 1, 2, 2, 1, 2, 2, 2, 2, 2, 2, 2, 2, 1, 2, 2, 1, 2, 2, 2, 2, 1, 4, 4, 1, 2, 2, 2, 2, 1, 2, 2, 1, 2, 2, 2, 2, 2, 2, 2, 2, 1, 2, 2, 1, 2, 2, 2, 2, 1, 4, 4, 1, 1, 1, 1, 1, 1, 2, 2, 1, 1, 1, 1, 2, 2, 1, 1, 1, 1, 2, 2, 1, 1, 1, 1, 1, 1, 4, 4, 4, 4, 4, 4, 4, 1, 2, 2, 2, 2, 2, 1, 2, 2, 1, 2, 2, 2, 2, 2, 1, 4, 4, 4, 4, 4, 4, 4, 4, 4, 4, 4, 4, 1, 2, 2, 2, 2, 2, 1, 2, 2, 1, 2, 2, 2, 2, 2, 1, 4, 4, 4, 4, 4, 4, 4, 4, 4, 4, 4, 4, 1, 2, 2, 1, 1, 1, 1, 1, 1, 1, 1, 1, 1, 2, 2, 1, 4, 4, 4, 4, 4, 4, 4, 4, 4, 4, 4, 4, 1, 2, 2, 1, 4, 4, 4, 4, 4, 4, 4, 4, 1, 2, 2, 1, 4, 4, 4, 4, 4, 4, 4, 4, 4, 4, 4, 4, 1, 2, 2, 1, 4, 4, 4, 4, 4, 4, 4, 4, 1, 2, 2, 1, 4, 4, 4, 4, 4, 4, 1, 1, 1, 1, 1, 1, 1, 1, 1, 1, 4, 4, 4, 4, 4, 4, 4, 4, 1, 1, 1, 1, 1, 1, 1, 1, 1, 1, 4, 4, 4, 4, 4, 4, 1, 2, 2, 1, 4, 4, 4, 4, 4, 4, 4, 4, 1, 2, 2, 1, 4, 4, 4, 4, 4, 4, 4, 4, 4, 4, 4, 4, 1, 2, 2, 1, 4, 4, 4, 4, 4, 4, 4, 4, 1, 2, 2, 1, 4, 4, 4, 4, 4, 4, 4, 4, 4, 4, 4, 4, 1, 2, 2, 1, 1, 1, 1, 1, 1, 1, 1, 1, 1, 2, 2, 1, 4, 4, 4, 4, 4, 4, 4, 4, 4, 4, 4, 4, 1, 2, 2, 1, 2, 2, 2, 2, 2, 2, 2, 2, 1, 2, 2, 1, 4, 4, 4, 4, 4, 4, 4, 4, 4, 4, 4, 4, 1, 2, 2, 1, 2, 2, 2, 2, 2, 2, 2, 2, 1, 2, 2, 1, 4, 4, 4, 4, 4, 4, 4, 1, 1, 1, 1, 1, 1, 1, 1, 1, 1, 1, 1, 2, 2, 1, 1, 1, 1, 1, 1, 1, 1, 1, 1, 1, 1, 4, 4, 1, 2, 2, 2, 2, 1, 2, 2, 2, 2, 2, 1, 2, 2, 1, 2, 2, 2, 2, 2, 1, 2, 2, 2, 2, 1, 4, 4, 1, 2, 2, 2, 2, 1, 2, 2, 2, 2, 2, 1, 2, 2, 1, 2, 2, 2, 2, 2, 1, 2, 2, 2, 2, 1, 4, 4, 1, 1, 1, 2, 2, 1, 1, 1, 1, 1, 1, 1, 1, 1, 1, 1, 1, 1, 1, 1, 1, 2, 2, 1, 1, 1, 4, 4, 4, 4, 1, 2, 2, 1, 2, 2, 1, 2, 2, 2, 2, 2, 2, 2, 2, 1, 2, 2, 1, 2, 2, 1, 4, 4, 4, 4, 4, 4, 1, 2, 2, 1, 2, 2, 1, 2, 2, 2, 2, 2, 2, 2, 2, 1, 2, 2, 1, 2, 2, 1, 4, 4, 4, 4, 1, 1, 1, 1, 1, 1, 2, 2, 1, 1, 1, 1, 2, 2, 1, 1, 1, 1, 2, 2, 1, 1, 1, 1, 1, 1, 4, 4, 1, 2, 2, 2, 2, 2, 2, 2, 2, 2, 2, 1, 2, 2, 1, 2, 2, 2, 2, 2, 2, 2, 2, 2, 2, 1, 4, 4, 1, 2, 2, 2, 2, 2, 2, 2, 2, 2, 2, 1, 2, 2, 1, 2, 2, 2, 2, 2, 2, 2, 2, 2, 2, 1, 4, 4, 1, 1, 1, 1, 1, 1, 1, 1, 1, 1, 1, 1, 1, 1, 1, 1, 1, 1, 1, 1, 1, 1, 1, 1, 1, 1, 4, 4, 4, 4, 4, 4, 4, 4, 4, 4, 4, 4, 4, 4, 4, 4, 4, 4, 4, 4, 4, 4, 4, 4, 4, 4, 4, 4, 4, 4, 4, 4, 4, 4, 4, 4, 4, 4, 4, 4, 4, 4, 4, 4, 4, 4, 4, 4, 4, 4, 4, 4, 4, 4, 4, 4, 4, 4, 4, 4, 4, 4, 4, 4, 4, 4, 4, 4, 4, 4, 4, 4, 4, 4, 4, 4, 4, 4, 4, 4, 4, 4, 4, 4, 4, 4, 4, 4, 4, 4, 4, 4, 4, 4, 4, 4, 4, 4, 4, 4, 4, 4, 4, 4, 4, 4, 4, 4, 4, 4, 4, 4, 4, 4, 4, 4, 4, 4, 4, 4, 4, 4, 4, 4, 4, 4, 4, 4, 4, 4, 4, 4, 4, 4, 4, 4, 4, 4, 4, 4, 4],
         "height":36,
         "name":"Capa de Patrones 1",
         "opacity":1,
         "type":"tilelayer",
         "visible":true,
         "width":28,
         "x":0,
         "y":0
        }],
 "nextobjectid":1,
 "orientation":"orthogonal",
 "renderorder":"right-down",
 "tiledversion":"1.0.2",
 "tileheight":32,
 "tilesets":[
        {
         "firstgid":1,
         "source":"untitled.tsx"
        }, 
        {
         "firstgid":2,
         "source":"bloqueos.tsx"
        }, 
        {
         "firstgid":3,
         "source":"bloqueos.tsx"
        }, 
        {
         "firstgid":4,
         "source":"home.tsx"
        }],
 "tilewidth":32,
 "type":"map",
 "version":1,
 "width":28
}